deprecated/hello.py
thegraph_mcp-0.1.0.dist-info/licenses/LICENSE
thegraph_mcp-0.1.0.dist-info/METADATA
thegraph_mcp-0.1.0.dist-info/WHEEL
thegraph_mcp-0.1.0.dist-info/top_level.txt
thegraph_mcp-0.1.0.dist-info/RECORD
